HW2/HW2_114010005_A1.v
module DEMUX(A, S, X, Y, Z);
    input A;
    input [1:0] S;
    output X, Y, Z;

    // behavioural, tri-state description
    // 依照作業圖片的真值表：
    //   S=00 -> X,Y,Z 皆為 Hi-Z (未選取任何輸出)
    //   S=01 -> X = A
    //   S=10 -> Y = A
    //   S=11 -> Z = A
    // 未被選到的輸出則變成高阻抗 (z)
    assign X = (S == 2'b01) ? A : 1'bz;
    assign Y = (S == 2'b10) ? A : 1'bz;
    assign Z = (S == 2'b11) ? A : 1'bz;

endmodule

HW2/HW2_114010005_A2.v
`timescale 1ns / 1ps

module DEMUX_tb;

    reg A;
    reg [1:0] S;
    wire X, Y, Z;

    // instantiate the DEMUX (device under test)
    DEMUX uut (
        .A(A),
        .S(S),
        .X(X),
        .Y(Y),
        .Z(Z)
    );

    // 產生 GTKWave 要看的波形檔
    initial begin
        $dumpfile("DEMUX.vcd");
        $dumpvars(0, DEMUX_tb);
    end

    // 窮舉所有 8 種輸入組合 (A: 2 種 x S: 4 種)
    initial begin
        A = 0; S = 2'b00;
        #10 A = 1; S = 2'b00;
        #10 A = 0; S = 2'b01;
        #10 A = 1; S = 2'b01;
        #10 A = 0; S = 2'b10;
        #10 A = 1; S = 2'b10;
        #10 A = 0; S = 2'b11;
        #10 A = 1; S = 2'b11;
        #10 $finish;
    end

    // 在 terminal 印出每個時間點的訊號，方便對照波形
    initial begin
        $monitor("time=%0t | A=%b S=%b || X=%b Y=%b Z=%b", $time, A, S, X, Y, Z);
    end

endmodule

HW2/DEMUX.vcd
$date
	Sat Aug 08 15:45:39 2026
$end
$version
	Icarus Verilog
$end
$timescale
	1ps
$end
$scope module DEMUX_tb $end
$var wire 1 ! Z $end
$var wire 1 " Y $end
$var wire 1 # X $end
$var reg 1 $ A $end
$var reg 2 % S [1:0] $end
$scope module uut $end
$var wire 1 $ A $end
$var wire 2 & S [1:0] $end
$var wire 1 ! Z $end
$var wire 1 " Y $end
$var wire 1 # X $end
$upscope $end
$upscope $end
$enddefinitions $end
$comment Show the parameter values. $end
$dumpall
$end
#0
$dumpvars
b0 &
b0 %
0$
z#
z"
z!
$end
#10000
1$
#20000
0#
b1 %
b1 &
0$
#30000
1#
1$
#40000
0"
z#
b10 %
b10 &
0$
#50000
1"
1$
#60000
0!
z"
b11 %
b11 &
0$
#70000
1!
1$
