HW2/HW2_114010005_B1.v
`timescale 1ns/1ps
module DFF(D, CLK, Q, nQ);
    input D, CLK;
    output Q, nQ;

    wire nD, nCLK;
    wire nS1, nR1, Q1, nQ1;
    wire nS2, nR2;

    // inverters: 0 delay (no #delay specified)
    not (nD, D);
    not (nCLK, CLK);

    // ---- Master latch (transparent when CLK = 1) ----
    nand #2 g1(nS1, D,  CLK);
    nand #2 g2(nR1, nD, CLK);
    nand #2 g3(Q1,  nS1, nQ1);
    nand #2 g4(nQ1, nR1, Q1);

    // ---- Slave latch (transparent when CLK = 0, i.e. nCLK = 1) ----
    nand #2 g5(nS2, Q1,  nCLK);
    nand #2 g6(nR2, nQ1, nCLK);
    nand #2 g7(Q,  nS2, nQ);
    nand #2 g8(nQ, nR2, Q);

endmodule

HW2/HW2_114010005_B3.v
`timescale 1ns/1ps
module DFF_setup_tb;
    reg D, CLK;
    wire Q, nQ;

    DFF uut(.D(D), .CLK(CLK), .Q(Q), .nQ(nQ));

    initial begin
        $dumpfile("DFF_setup.vcd");
        $dumpvars(0, DFF_setup_tb);
    end

    initial $monitor("t=%0t CLK=%b D=%b | Q=%b nQ=%b", $time, CLK, D, Q, nQ);

    // ============================================================
    // 測試流程：
    //  (1) 先做power-up + 讓 Q 穩定在 1 (D=1擺一段時間，經過一次edge)
    //  (2) case A: D 在 CLK 下降緣「前 6ns」變成0 (剛好等於算出的setup time) -> 應該成功變成0
    //  (3) case B: D 在 CLK 下降緣「前 2ns」才變成0 (明顯小於setup time) -> 應該失敗，Q 應該還停在 1（或跑出不確定/錯誤值）
    // ============================================================

    initial begin
        // ---- power up ----
        D = 1; CLK = 1;
        #10 CLK = 0;   // 第一次下降緣，Q應該被設成1
        #10 CLK = 1;

        // ---- Case A: setup time 剛好滿足 (D 在edge前 6ns 改變) ----
        #20;                 // CLK=1 一段時間, 讓狀態穩定
        #14 D = 0;            // D 在此時改變 (1->0)
        #6  CLK = 0;          // edge 發生在 D 改變後 6ns -> 滿足 setup time, 預期 Q 成功變成 0
        #20 CLK = 1;
        #10 D = 1;             // 把D跟Q都重置回1，準備下一個測試
        #10 CLK = 0;
        #10 CLK = 1;

        // ---- Case B: setup time 不足 (D 在edge前只有 2ns 改變) ----
        #20;
        #4  D = 0;             // D 在此時改變 (1->0)
        #2  CLK = 0;           // edge 發生在 D 改變後只有 2ns -> 違反 setup time, 預期 Q 沒有正確變成 0
        #20 CLK = 1;

        #20 $finish;
    end
endmodule

HW2/DFF_setup.vcd
$date
	Sat Aug 08 16:59:16 2026
$end
$version
	Icarus Verilog
$end
$timescale
	1ps
$end
$scope module DFF_setup_tb $end
$var wire 1 ! nQ $end
$var wire 1 " Q $end
$var reg 1 # CLK $end
$var reg 1 $ D $end
$scope module uut $end
$var wire 1 # CLK $end
$var wire 1 $ D $end
$var wire 1 " Q $end
$var wire 1 % Q1 $end
$var wire 1 & nCLK $end
$var wire 1 ' nD $end
$var wire 1 ! nQ $end
$var wire 1 ( nQ1 $end
$var wire 1 ) nR1 $end
$var wire 1 * nR2 $end
$var wire 1 + nS1 $end
$var wire 1 , nS2 $end
$upscope $end
$upscope $end
$enddefinitions $end
$comment Show the parameter values. $end
$dumpall
$end
#0
$dumpvars
x,
x+
x*
x)
x(
0'
0&
x%
1$
1#
x"
x!
$end
#2000
1,
1*
1)
0+
#4000
1%
#6000
0(
#10000
1&
0#
#12000
0,
1+
#14000
1"
#16000
0!
#20000
0&
1#
#22000
1,
0+
#54000
1'
0$
#56000
0)
1+
#58000
1(
#60000
1&
0%
0#
#62000
0*
1)
#64000
1!
#66000
0"
#80000
0&
1#
#82000
1*
0)
#90000
0'
1$
#92000
1)
0+
#94000
1%
#96000
0(
#100000
1&
0#
#102000
0,
1+
#104000
1"
#106000
0!
#110000
0&
1#
#112000
1,
0+
#134000
1'
0$
#136000
1&
0)
1+
0#
#138000
0,
1(
1)
#140000
0*
0%
0(
#142000
1!
1(
1,
1*
1%
#144000
0*
0%
0"
0!
0(
0,
#146000
1(
1,
1!
1*
1%
1"
#148000
0*
0%
0"
0(
0,
0!
#150000
1(
1,
1!
1*
1%
1"
#152000
0*
0%
0"
0(
0,
0!
#154000
1(
1,
1!
1*
1%
1"
#156000
0&
0*
0%
0"
0(
0,
0!
1#
#158000
1(
1,
1!
1*
1%
1"
0)
#160000
0%
0"
0!
#162000
1!
1"
#164000
0"
0!
#166000
1!
1"
#168000
0"
0!
#170000
1!
1"
#172000
0"
0!
#174000
1!
1"
#176000
0"
0!
