HW2/HW2_114010005_B1.v
`timescale 1ns/1ps
module DFF(D, CLK, Q, nQ);
    input D, CLK;
    output Q, nQ;

    wire nD, nCLK;
    wire nS1, nR1, Q1, nQ1;
    wire nS2, nR2;

    // inverters: 0 delay (no #delay specified)
    not (nD, D);
    not (nCLK, CLK);

    // ---- Master latch (transparent when CLK = 1) ----
    nand #2 g1(nS1, D,  CLK);
    nand #2 g2(nR1, nD, CLK);
    nand #2 g3(Q1,  nS1, nQ1);
    nand #2 g4(nQ1, nR1, Q1);

    // ---- Slave latch (transparent when CLK = 0, i.e. nCLK = 1) ----
    nand #2 g5(nS2, Q1,  nCLK);
    nand #2 g6(nR2, nQ1, nCLK);
    nand #2 g7(Q,  nS2, nQ);
    nand #2 g8(nQ, nR2, Q);

endmodule

HW2/HW2_114010005_B2.v
`timescale 1ns/1ps
module DFF_func_tb;
    reg D, CLK;
    wire Q, nQ;

    DFF uut(.D(D), .CLK(CLK), .Q(Q), .nQ(nQ));

    initial begin
        $dumpfile("DFF_func.vcd");
        $dumpvars(0, DFF_func_tb);
    end

    initial begin
        D   = 0;
        CLK = 1;      // 先讓CLK=1一段時間(>4ns), 使Master latch resolve成已知值
        #20 CLK = 0;  // 第一次下降緣：讓Slave也跟著resolve成已知值；Q應該變成 D=0
        #20 CLK = 1;
        #10 D = 1;    // 在CLK=1的中間改變 D
        #30 CLK = 0;  // 下降緣：Q應該變成 1
        #20 CLK = 1;
        #10 D = 0;    // 在CLK=1的中間改變 D
        #30 CLK = 0;  // 下降緣：Q應該變回 0
        #20 CLK = 1;
        #40 $finish;
    end

    initial $monitor("t=%0t CLK=%b D=%b | Q=%b nQ=%b", $time, CLK, D, Q, nQ);
endmodule

HW2/DFF_func.vcd
$date
	Sat Aug 08 16:54:31 2026
$end
$version
	Icarus Verilog
$end
$timescale
	1ps
$end
$scope module DFF_func_tb $end
$var wire 1 ! nQ $end
$var wire 1 " Q $end
$var reg 1 # CLK $end
$var reg 1 $ D $end
$scope module uut $end
$var wire 1 # CLK $end
$var wire 1 $ D $end
$var wire 1 " Q $end
$var wire 1 % Q1 $end
$var wire 1 & nCLK $end
$var wire 1 ' nD $end
$var wire 1 ! nQ $end
$var wire 1 ( nQ1 $end
$var wire 1 ) nR1 $end
$var wire 1 * nR2 $end
$var wire 1 + nS1 $end
$var wire 1 , nS2 $end
$upscope $end
$upscope $end
$enddefinitions $end
$comment Show the parameter values. $end
$dumpall
$end
#0
$dumpvars
x,
x+
x*
x)
x(
1'
0&
x%
0$
1#
x"
x!
$end
#2000
1,
1*
0)
1+
#4000
1(
#6000
0%
#20000
1&
0#
#22000
0*
1)
#24000
1!
#26000
0"
#40000
0&
1#
#42000
1*
0)
#50000
0'
1$
#52000
1)
0+
#54000
1%
#56000
0(
#80000
1&
0#
#82000
0,
1+
#84000
1"
#86000
0!
#100000
0&
1#
#102000
1,
0+
#110000
1'
0$
#112000
0)
1+
#114000
1(
#116000
0%
#140000
1&
0#
#142000
0*
1)
#144000
1!
#146000
0"
#160000
0&
1#
#162000
1*
0)
