HW3/HW3_114010005.v
`timescale 1ns/1ps

module Warn_Pattern (clk, rst_n, in, out);
input clk, rst_n;
input in;
output [2-1:0] out;

reg [1:0] out;
reg [3:0] state, next_state;

//state encoding
parameter IDLE  = 4'd0,
          S0    = 4'd1,
          S1    = 4'd2,
          S01   = 4'd3,
          S10   = 4'd4,
          S011  = 4'd5,
          S101  = 4'd6,
          M1011 = 4'd7,
          M0110 = 4'd8;

//1. 狀態暫存器：同步 reset，時序邏輯
always @(posedge clk) begin
    if (!rst_n)
        state <= IDLE;
    else
        state <= next_state;
end

//2. 下一狀態邏輯：組合邏輯，對應你畫的那張圖
always @(*) begin
    case (state)
        IDLE:  next_state = in ? S1    : S0;
        S0:    next_state = in ? S01   : S0;
        S1:    next_state = in ? S1    : S10;
        S01:   next_state = in ? S011  : S10;
        S10:   next_state = in ? S101  : S0;
        S011:  next_state = in ? S1    : M0110;
        S101:  next_state = in ? M1011 : S10;
        M1011: next_state = in ? S1    : M0110;
        M0110: next_state = in ? S101  : S0;
        default: next_state = IDLE;
    endcase
end

//3. 輸出邏輯：組合邏輯，只看目前 state（Moore machine）
always @(*) begin
    case (state)
        IDLE:  out = 2'b11;
        M1011: out = 2'b01;
        M0110: out = 2'b01;
        default: out = 2'b00;
    endcase
end

endmodule

HW3/HW3_114010005_tb.v
`timescale 1ns/1ps

module Warn_Pattern_t;
reg clk = 1'b1;
reg rst_n = 1'b1;
reg in = 1'b0;
wire [2-1:0] out;

// specify duration of a clock cycle.
parameter cyc = 10;

// generate clock.
always #(cyc/2) clk = ~clk;

//the module that you designed
Warn_Pattern WP (
    .clk (clk),
    .rst_n (rst_n),
    .in (in),
    .out (out)
);

//this blocks is for creating the waveform
initial begin
    $dumpfile("HW3_result.vcd");
    $dumpvars(0,Warn_Pattern_t);
end

//--- 把重複動作包成 task ---
task apply_bit(input bit_in);
    begin
        @(negedge clk);
        in = bit_in;
    end
endtask

initial begin
    // Test 1: reset 行為，此時 out 應該要是 11
    rst_n = 1'b0;
    @(negedge clk);
    @(negedge clk);
    rst_n = 1'b1;

    // Test 2: 餵入 "1011"，應該在第4個bit進去後偵測到，out=01
    apply_bit(1'b1);
    apply_bit(1'b0);
    apply_bit(1'b1);
    apply_bit(1'b1);

    // Test 3: 餵入 "0110"，應該偵測到，out=01
    apply_bit(1'b0);
    apply_bit(1'b1);
    apply_bit(1'b1);
    apply_bit(1'b0);

    // Test 4: 測試重疊情況 "10110"
    // 前4碼1011會先命中一次，接著0110又會命中一次
    apply_bit(1'b1);
    apply_bit(1'b0);
    apply_bit(1'b1);
    apply_bit(1'b1);
    apply_bit(1'b0);

    // Test 5: 測試中途再 reset 一次
    rst_n = 1'b0;
    @(negedge clk);
    rst_n = 1'b1;

    // Test 6: 完全不 match，維持 S0
    apply_bit(1'b0);
    apply_bit(1'b0);
    apply_bit(1'b0);

    rst_n = 1'b0;
    @(negedge clk);
    rst_n = 1'b1;

    // Test 7: 完全不 match，維持 S1
    apply_bit(1'b1);
    apply_bit(1'b1);
    apply_bit(1'b1);

    rst_n = 1'b0;
    @(negedge clk);
    rst_n = 1'b1;

    // Test 8: 比對到一半斷掉 (S1->S10->S0)
    apply_bit(1'b1);
    apply_bit(1'b0);
    apply_bit(1'b0);

    rst_n = 1'b0;
    @(negedge clk);
    rst_n = 1'b1;

    // Test 9: 藍色斜線 S011 -> S1 (收到1沒有形成0110)
    apply_bit(1'b0);
    apply_bit(1'b1);
    apply_bit(1'b1);
    apply_bit(1'b1);  // 這裡應該跳回 S1，不是 M0110

    rst_n = 1'b0;
    @(negedge clk);
    rst_n = 1'b1;

    // Test 10: 連續命中兩次 (不重疊)
    apply_bit(1'b1); apply_bit(1'b0); apply_bit(1'b1); apply_bit(1'b1); // 第一次 match
    apply_bit(1'b1); apply_bit(1'b0); apply_bit(1'b1); apply_bit(1'b1); // 第二次 match

    rst_n = 1'b0;
    @(negedge clk);
    rst_n = 1'b1;

    // Test 11: 反向重疊 011011
    apply_bit(1'b0); apply_bit(1'b1); apply_bit(1'b1); apply_bit(1'b0); // 0110 命中
    apply_bit(1'b1); apply_bit(1'b1); // 接著湊出 1011 應該再命中一次

    // Test 12: 比對途中 reset
    apply_bit(1'b1);
    apply_bit(1'b0);
    rst_n = 1'b0;
    @(negedge clk);
    rst_n = 1'b1;

    // 全部測試跑完，最後緩衝幾個 cycle 再結束
    #(cyc*3);
    $finish;
end

endmodule

HW3/HW3_result.vcd
$date
	Thu Aug 20 21:29:14 2026
$end
$version
	Icarus Verilog
$end
$timescale
	1ps
$end
$scope module Warn_Pattern_t $end
$var wire 2 ! out [1:0] $end
$var parameter 32 " cyc $end
$var reg 1 # clk $end
$var reg 1 $ in $end
$var reg 1 % rst_n $end
$scope module WP $end
$var wire 1 # clk $end
$var wire 1 $ in $end
$var wire 1 % rst_n $end
$var parameter 4 & IDLE $end
$var parameter 4 ' M0110 $end
$var parameter 4 ( M1011 $end
$var parameter 4 ) S0 $end
$var parameter 4 * S01 $end
$var parameter 4 + S011 $end
$var parameter 4 , S1 $end
$var parameter 4 - S10 $end
$var parameter 4 . S101 $end
$var reg 4 / next_state [3:0] $end
$var reg 2 0 out [1:0] $end
$var reg 4 1 state [3:0] $end
$upscope $end
$scope task apply_bit $end
$var reg 1 2 bit_in $end
$upscope $end
$upscope $end
$enddefinitions $end
$comment Show the parameter values. $end
$dumpall
b110 .
b100 -
b10 ,
b101 +
b11 *
b1 )
b111 (
b1000 '
b0 &
b1010 "
$end
#0
$dumpvars
x2
b0 1
b11 0
b1 /
0%
0$
1#
b11 !
$end
#5000
0#
#10000
1#
#15000
12
1%
0#
#20000
b0 !
b0 0
b1 1
1#
#25000
b11 /
02
1$
0#
#30000
b101 /
b11 1
1#
#35000
b100 /
12
0$
0#
#40000
b1 /
b100 1
1#
#45000
b110 /
1$
0#
#50000
b111 /
b110 1
1#
#55000
02
0#
#60000
b1 !
b1 0
b10 /
b111 1
1#
#65000
b1000 /
12
0$
0#
#70000
b1 /
b1000 1
1#
#75000
b110 /
1$
0#
#80000
b0 !
b0 0
b111 /
b110 1
1#
#85000
02
0#
#90000
b1 !
b1 0
b10 /
b111 1
1#
#95000
b1000 /
12
0$
0#
#100000
b1 /
b1000 1
1#
#105000
b110 /
02
1$
0#
#110000
b0 !
b0 0
b111 /
b110 1
1#
#115000
b100 /
12
0$
0#
#120000
b1 /
b100 1
1#
#125000
b110 /
1$
0#
#130000
b111 /
b110 1
1#
#135000
02
0#
#140000
b1 !
b1 0
b10 /
b111 1
1#
#145000
b1000 /
0%
0$
0#
#150000
b11 !
b11 0
b1 /
b0 1
1#
#155000
1%
0#
#160000
b0 !
b0 0
b1 1
1#
#165000
0#
#170000
1#
#175000
0#
#180000
1#
#185000
0%
0#
#190000
b11 !
b11 0
b0 1
1#
#195000
12
1%
0#
#200000
b0 !
b0 0
b1 1
1#
#205000
b11 /
1$
0#
#210000
b101 /
b11 1
1#
#215000
0#
#220000
b10 /
b101 1
1#
#225000
0%
0#
#230000
b11 !
b11 0
b0 1
1#
#235000
1%
0#
#240000
b0 !
b0 0
b10 1
1#
#245000
02
0#
#250000
1#
#255000
b100 /
0$
0#
#260000
b1 /
b100 1
1#
#265000
0%
0#
#270000
b11 !
b11 0
b0 1
1#
#275000
1%
0#
#280000
b0 !
b0 0
b1 1
1#
#285000
12
0#
#290000
1#
#295000
b11 /
1$
0#
#300000
b101 /
b11 1
1#
#305000
0#
#310000
b10 /
b101 1
1#
#315000
0%
0#
#320000
b11 !
b11 0
b0 1
1#
#325000
1%
0#
#330000
b0 !
b0 0
b10 1
1#
#335000
02
0#
#340000
1#
#345000
b100 /
12
0$
0#
#350000
b1 /
b100 1
1#
#355000
b110 /
1$
0#
#360000
b111 /
b110 1
1#
#365000
0#
#370000
b1 !
b1 0
b10 /
b111 1
1#
#375000
02
0#
#380000
b0 !
b0 0
b10 1
1#
#385000
b100 /
12
0$
0#
#390000
b1 /
b100 1
1#
#395000
b110 /
1$
0#
#400000
b111 /
b110 1
1#
#405000
0%
0#
#410000
b11 !
b11 0
b10 /
b0 1
1#
#415000
02
1%
0#
#420000
b0 !
b0 0
b10 1
1#
#425000
b100 /
12
0$
0#
#430000
b1 /
b100 1
1#
#435000
b110 /
1$
0#
#440000
b111 /
b110 1
1#
#445000
02
0#
#450000
b1 !
b1 0
b10 /
b111 1
1#
#455000
b1000 /
12
0$
0#
#460000
b1 /
b1000 1
1#
#465000
b110 /
1$
0#
#470000
b0 !
b0 0
b111 /
b110 1
1#
#475000
0#
#480000
b1 !
b1 0
b10 /
b111 1
1#
#485000
02
0#
#490000
b0 !
b0 0
b10 1
1#
#495000
b100 /
0%
0$
0#
#500000
b11 !
b11 0
b1 /
b0 1
1#
#505000
1%
0#
#510000
b0 !
b0 0
b1 1
1#
